aesy/__init__.py
aesy/cipher.py
aesy-1.0.4.dist-info/licenses/LICENSE
aesy-1.0.4.dist-info/METADATA
aesy-1.0.4.dist-info/WHEEL
aesy-1.0.4.dist-info/top_level.txt
aesy-1.0.4.dist-info/RECORD
