Metadata-Version: 2.4
Name: aesy
Version: 1.0.4
Summary: AESY multi-layer encryption algorithm
Home-page: https://gitlab.com/gubir34/aesy/
Author: Gubir34
Author-email: gubir34 <canteoman15@gmail.com>
License: MIT
Classifier: Programming Language :: Python :: 3
Classifier: License :: OSI Approved :: MIT License
Requires-Python: >=3.8
License-File: LICENSE
Dynamic: author
Dynamic: home-page
Dynamic: license-file
Dynamic: requires-python
